Workbook

Sheet Cost Structure
A1: GROUNDTRUTH DOCUMENT DIGITIZATION PLATFORM
A2: Cost Structure Analysis (South Africa)
A4: Exchange Rate Assumption: | B4: 20 | C4: per USD
A6: LANDINGAI API COSTS
A7: Metric | B7: USD | C7: ZAR
A8: Cost per credit | B8: 0.00909 | C8: =B8*B4 -> 0.1818
A9: Avg credits per document (parse + extract) | B9: 2.5 | C9: =B9*B4 -> 50
A10: Cost per document | B10: =B8*B9 -> 0.022725 | C10: =B10*B4 -> 0.4545
A11: Cost per page (avg 5 pages/doc) | B11: =B10/5 -> 0.004545 | C11: =C10/5 -> 0.0909
A13: MONTHLY INFRASTRUCTURE COSTS
A14: Component | B14: Low (USD) | C14: High (USD) | D14: Low (ZAR) | E14: High (ZAR)
A15: Supabase Database | B15: 25 | C15: 25 | D15: =B15*B4 -> 500 | E15: =C15*B4 -> 500
A16: Backend Hosting (EC2/Cloud Run) | B16: 50 | C16: 500 | D16: =B16*B4 -> 1000 | E16: =C16*B4 -> 10000
A17: Storage (S3/GCS) - 1-10TB | B17: 20 | C17: 200 | D17: =B17*B4 -> 400 | E17: =C17*B4 -> 4000
A18: Vector DB (Qdrant Cloud/Managed) | B18: 70 | C18: 300 | D18: =B18*B4 -> 1400 | E18: =C18*B4 -> 6000
A19: CDN & Load Balancing | B19: 20 | C19: 100 | D19: =B19*B4 -> 400 | E19: =C19*B4 -> 2000
A20: Monitoring & Logging | B20: 50 | C20: 200 | D20: =B20*B4 -> 1000 | E20: =C20*B4 -> 4000
A21: TOTAL MONTHLY INFRASTRUCTURE | B21: =SUM(B15:B20) -> 235 | C21: =SUM(C15:C20) -> 1325 | D21: =SUM(D15:D20) -> 4700 | E21: =SUM(E15:E20) -> 26500
A23: COST PER DOCUMENT SUMMARY
A24: Metric | B24: ZAR
A25: LandingAI Cost per Document | B25: =C10 -> 0.4545
A26: Infrastructure Cost per 1,000 docs (Low) | B26: =D21/1000 -> 4.7
A27: Infrastructure Cost per 1,000 docs (High) | B27: =E21/1000 -> 26.5
A29: TOTAL VARIABLE COST (Low volume) | B29: =B25+B27 -> 26.9545
A30: TOTAL VARIABLE COST (High volume) | B30: =B25+B26 -> 5.1545

Sheet Pricing Tiers
A1: GROUNDTRUTH - PRICING TIERS
A2: Credit-Based SaaS Pricing (Rand)
B5: STARTER | C5: PROFESSIONAL | D5: ENTERPRISE | E5: GOVERNMENT
A6: Monthly Price | B6: 10000 | C6: 50000 | D6: 200000 | E6: Custom
A7: Document Credits | B7: 500 | C7: 3000 | D7: 15000 | E7: 50,000+
A8: Cost per Document | B8: =B6/B7 -> 20 | C8: =C6/C7 -> 16.666667 | D8: =D6/D7 -> 13.333333 | E8: 8-12
A9: Users Included | B9: 2 | C9: 10 | D9: Unlimited | E9: Unlimited
A10: Support Level | B10: Email | C10: Priority Email | D10: Dedicated | E10: 24/7 + SLA
A11: Custom Workflows | B11: No | C11: Yes | D11: Yes | E11: Yes
A12: API Access | B12: Limited | C12: Full | D12: Full | E12: Full + White-label
A13: Data Retention | B13: 1 year | C13: 3 years | D13: 5 years | E13: Configurable
A14: Training Included | B14: Self-service | C14: 2 sessions | D14: Unlimited | E14: On-site
A17: MARGIN ANALYSIS (per document)
A18: Metric | B18: STARTER | C18: PROFESSIONAL | D18: ENTERPRISE
A19: Revenue per Document | B19: =B8 -> 20 | C19: =C8 -> 16.666667 | D19: =D8 -> 13.333333
A20: Cost per Document (High infra) | B20: ='Cost Structure'!B29 -> 26.9545 | C20: ='Cost Structure'!B29 -> 26.9545 | D20: ='Cost Structure'!B30 -> 5.1545
A21: Gross Profit per Document | B21: =B19-B20 -> -6.9545 | C21: =C19-C20 -> -10.287833 | D21: =D19-D20 -> 8.1788333
A22: Gross Margin % | B22: =B21/B19 -> -0.347725 | C22: =C21/C19 -> -0.61727 | D22: =D21/D19 -> 0.6134125
A24: OVERAGE PRICING
A25: Additional documents beyond plan: | B25: 15 | C25: per document
A26: Volume discount (>10,000 docs/month): | B26: 10 | C26: per document

Sheet 3-Year Projections
A1: GROUNDTRUTH - 3-YEAR REVENUE PROJECTIONS
A2: Conservative Growth Scenario
A4: CUSTOMER GROWTH
A5: Metric | B5: Year 1 | C5: Year 2 | D5: Year 3
A6: Starter Tier Customers | B6: 8 | C6: 15 | D6: 25
A7: Professional Tier Customers | B7: 3 | C7: 8 | D7: 15
A8: Enterprise Tier Customers | B8: 1 | C8: 3 | D8: 6
A9: Government Contracts | B9: 0 | C9: 1 | D9: 2
A11: MONTHLY RECURRING REVENUE
A12: Revenue Source | B12: Year 1 | C12: Year 2 | D12: Year 3
A13: Starter MRR | B13: =B6*'Pricing Tiers'!B6 -> 80000 | C13: =C6*'Pricing Tiers'!B6 -> 150000 | D13: =D6*'Pricing Tiers'!B6 -> 250000
A14: Professional MRR | B14: =B7*'Pricing Tiers'!C6 -> 150000 | C14: =C7*'Pricing Tiers'!C6 -> 400000 | D14: =D7*'Pricing Tiers'!C6 -> 750000
A15: Enterprise MRR | B15: =B8*'Pricing Tiers'!D6 -> 200000 | C15: =C8*'Pricing Tiers'!D6 -> 600000 | D15: =D8*'Pricing Tiers'!D6 -> 1200000
A16: Government MRR (avg) | B16: =B9*150000 -> 0 | C16: =C9*150000 -> 150000 | D16: =D9*150000 -> 300000
A17: TOTAL MRR | B17: =SUM(B13:B16) -> 430000 | C17: =SUM(C13:C16) -> 1300000 | D17: =SUM(D13:D16) -> 2500000
A19: ANNUAL PROJECTIONS
A20: Annual Recurring Revenue (ARR) | B20: =B17*12 -> 5160000 | C20: =C17*12 -> 15600000 | D20: =D17*12 -> 30000000
A21: Documents Processed (estimate) | B21: 100000 | C21: 300000 | D21: 650000
A22: Average Revenue per Document | B22: =B20/B21 -> 51.6 | C22: =C20/C21 -> 52 | D22: =D20/D21 -> 46.153846
A24: COST STRUCTURE
A25: Variable Costs (LandingAI) | B25: =B21*'Cost Structure'!C10 -> 45450 | C25: =C21*'Cost Structure'!C10 -> 136350 | D25: =D21*'Cost Structure'!C10 -> 295425
A26: Infrastructure Costs (annual) | B26: ='Cost Structure'!E21*12 -> 318000 | C26: ='Cost Structure'!E21*12*1.5 -> 477000 | D26: ='Cost Structure'!E21*12*2 -> 636000
A27: Staff Costs (2-5 FTE @ R40k/month) | B27: 960000 | C27: 1920000 | D27: 2400000
A28: Sales & Marketing | B28: 300000 | C28: 600000 | D28: 900000
A29: Total Operating Costs | B29: =SUM(B25:B28) -> 1623450 | C29: =SUM(C25:C28) -> 3133350 | D29: =SUM(D25:D28) -> 4231425
A31: PROFITABILITY
A32: Annual Revenue | B32: =B20 -> 5160000 | C32: =C20 -> 15600000 | D32: =D20 -> 30000000
A33: Total Costs | B33: =B29 -> 1623450 | C33: =C29 -> 3133350 | D33: =D29 -> 4231425
A34: Net Profit / (Loss) | B34: =B32-B33 -> 3536550 | C34: =C32-C33 -> 12466650 | D34: =D32-D33 -> 25768575
A35: Net Margin % | B35: =B34/B32 -> 0.68537791 | C35: =C34/C32 -> 0.79914423 | D35: =D34/D32 -> 0.8589525

Sheet Government Tender
A1: GOVERNMENT TENDER PRICING MODEL
A2: Per-Page & Volume Discount Structure
A4: PRICING ASSUMPTIONS
A5: Average pages per document: | B5: 5
A6: Your cost per page: | B6: ='Cost Structure'!C11 -> 0.0909
A9: TENDER PRICING STRUCTURE
A10: Volume Tier | B10: Pages | C10: Price per Page | D10: Example: 100k pages | E10: Your Margin
A11: Tier 1: Small | B11: 0 - 100,000 | C11: 1 | D11: =C11*100000 -> 100000 | E11: =(C11-B6)/C11 -> 0.9091
A12: Tier 2: Medium | B12: 100,001 - 500,000 | C12: 0.75 | D12: =C12*100000 -> 75000 | E12: =(C12-B6)/C12 -> 0.8788
A13: Tier 3: Large | B13: 500,001 - 2,000,000 | C13: 0.5 | D13: =C13*100000 -> 50000 | E13: =(C13-B6)/C13 -> 0.8182
A14: Tier 4: Enterprise | B14: 2,000,000+ | C14: 0.4 | D14: =C14*100000 -> 40000 | E14: =(C14-B6)/C14 -> 0.77275
A17: EXAMPLE TENDER SCENARIOS
A18: Scenario | B18: Total Pages | C18: Total Documents | D18: Contract Value | E18: Annual Revenue
A19: Provincial Health Dept - Pilot | B19: 50000 | C19: =B19/B5 -> 10000 | D19: =B19*C11 -> 50000 | E19: =D19 -> 50000
A20: Municipal Clinic Network | B20: 250000 | C20: =B20/B5 -> 50000 | D20: =B20*C11 -> 250000 | E20: =D20/3 -> 83333.333
A21: National Digitization Program | B21: 1500000 | C21: =B21/B5 -> 300000 | D21: =B21*C11 -> 1500000 | E21: =D21/3 -> 500000
A22: Multi-year Provincial Contract | B22: 5000000 | C22: =B22/B5 -> 1000000 | D22: =B22*C11 -> 5000000 | E22: =D22/3 -> 1666666.7
A25: COMPETITIVE POSITIONING
A26: Traditional Manual Digitization: | B26: R 0.50 - 2.00 | C26: per page
A27: Your AI-Powered Solution: | B27: R 0.40 - 1.00 | C27: per page (20-60% cheaper)
A28: Value Add: | B28: Searchable, Validated, RAG-enabled
